zonaite/__init__.py
zonaite/version.py
zonaite/forecast/__init__.py
zonaite/forecast/gfs.py
zonaite/forecast/ifs.py
zonaite/obser/__init__.py
zonaite/obser/desynop.py
zonaite-0.2.0.dist-info/METADATA
zonaite-0.2.0.dist-info/WHEEL
zonaite-0.2.0.dist-info/licenses/LICENSE
zonaite-0.2.0.dist-info/RECORD
