Metadata-Version: 2.4
Name: zonaite
Version: 0.2.0
Summary: 气象数据处理工具包
Author-email: Clarmy <clarmyleewt@outlook.com>
License-Expression: MIT
License-File: LICENSE
Requires-Python: >=3.8
Requires-Dist: boto3>=1.26.0
Requires-Dist: loguru>=0.7.0
Requires-Dist: pandas>=2.0.0
Requires-Dist: requests>=2.32.3
Requires-Dist: tqdm>=4.67.1
Provides-Extra: dev
Requires-Dist: pytest-cov>=4.0.0; extra == 'dev'
Requires-Dist: pytest>=7.0.0; extra == 'dev'
